Metadata-Version: 2.1
Name: setsGreatest
Version: 0.1.0
Summary: Find the greatest value among a bunch of numbers via my Logic using sets and lists
Author: SIDAGANA UDAY
Author-email: uday.sidgana@gmail.com
